setup.py
agentpolis/__init__.py
agentpolis/generate_config.py
agentpolis/init.py
agentpolis/prepare_map.py
agentpolis.egg-info/PKG-INFO
agentpolis.egg-info/SOURCES.txt
agentpolis.egg-info/dependency_links.txt
agentpolis.egg-info/requires.txt
agentpolis.egg-info/top_level.txt
agentpolis/config/__init__.py
agentpolis/config/agentpolis_config.py
agentpolis/resources/__init__.py
agentpolis/resources/config.cfg