Metadata-Version: 2.1
Name: agentpolis
Version: 0.2.0
Summary: service scripts for agentpolis simulation framework
Home-page: https://github.com/aicenter/agentpolis
Author: David Fiedler
Author-email: david.fido.fiedler@gmail.com
License: LGPL
Platform: UNKNOWN
Requires-Python: >=3.6
